Metadata-Version: 2.1
Name: pyndodax
Version: 0.3
Summary: A Python wrapper for indodax.com API with support for async i/o
Home-page: https://github.com/diwangs/pyndodax
Author: diwangs
Author-email: hi@diwangs.net
License: UNKNOWN
Keywords: bitcoin cryptocurrency trading indodax
Platform: UNKNOWN
Classifier: Development Status :: 1 - Planning
Classifier: Intended Audience :: Developers
Classifier: License :: OSI Approved :: Apache Software License
Classifier: Programming Language :: Python :: 3.7
Requires-Python: >=3.7
Provides-Extra: dev
